LICENSE
MANIFEST.in
README.md
VERSION
pyproject.toml
setup.py
version_helpers.py
config/config_template.ini
src/solana_nft.egg-info/PKG-INFO
src/solana_nft.egg-info/SOURCES.txt
src/solana_nft.egg-info/dependency_links.txt
src/solana_nft.egg-info/entry_points.txt
src/solana_nft.egg-info/requires.txt
src/solana_nft.egg-info/top_level.txt
src/solen/__init__.py
src/solen/context.py
src/solen/nft_client.py
src/solen/response.py
src/solen/sol_client.py
src/solen/token_client.py
src/solen/version.py
src/solen/core/__init__.py
src/solen/core/api.py
src/solen/core/constants.py
src/solen/core/errors.py
src/solen/core/metadata.py
src/solen/core/transactions.py
src/solen/utils/__init__.py
src/solen/utils/arweave.py
src/solen/utils/bulk_handler.py
src/solen/utils/config_parser.py
src/solen_cli/__init__.py
src/solen_cli/log_print.py
src/solen_cli/main.py
src/solen_cli/nft.py
src/solen_cli/table.py
src/solen_cli/token.py