Metadata-Version: 2.1
Name: solana-nft
Version: 0.0.1
Summary: Solana NFT Util
Home-page: UNKNOWN
Author: dusking
License: LICENSE
Platform: All
Requires-Python: >=3.7
License-File: LICENSE
